vectank/__init__.py
vectank/core.py
vectank/server.py
vectank/store.py
vectank/tank.py
vectank-0.2.0.dist-info/licenses/LICENSE
vectank-0.2.0.dist-info/METADATA
vectank-0.2.0.dist-info/WHEEL
vectank-0.2.0.dist-info/entry_points.txt
vectank-0.2.0.dist-info/top_level.txt
vectank-0.2.0.dist-info/RECORD
