Metadata-Version: 2.4
Name: VecTank
Version: 0.2.0
Summary: 軽量で高速なインメモリベクトル検索およびタンク操作ライブラリ
Home-page: https://github.com/satorunnlg/VecTank.git
Author: satorunnlg
Author-email: satorunnlg@gmail.com
Classifier: Programming Language :: Python :: 3
Classifier: Operating System :: OS Independent
Requires-Python: >=3.7
License-File: LICENSE
Requires-Dist: numpy
Dynamic: author
Dynamic: author-email
Dynamic: classifier
Dynamic: description
Dynamic: description-content-type
Dynamic: home-page
Dynamic: license-file
Dynamic: requires-dist
Dynamic: requires-python
Dynamic: summary
